vecspark/__init__.py
vecspark/main.py
vecspark-0.1.0.dist-info/METADATA
vecspark-0.1.0.dist-info/WHEEL
vecspark-0.1.0.dist-info/top_level.txt
vecspark-0.1.0.dist-info/RECORD
